LICENSE
MANIFEST.in
README.md
setup.py
django_infinite_scroll_pagination.egg-info/PKG-INFO
django_infinite_scroll_pagination.egg-info/SOURCES.txt
django_infinite_scroll_pagination.egg-info/dependency_links.txt
django_infinite_scroll_pagination.egg-info/not-zip-safe
django_infinite_scroll_pagination.egg-info/top_level.txt
infinite_scroll_pagination/__init__.py
infinite_scroll_pagination/paginator.py
infinite_scroll_pagination/serializers.py