Metadata-Version: 1.1
Name: django-infinite-scroll-pagination
Version: 1.2.1
Summary: infinite-scroll-pagination is a Django lib that implementsthe *seek method* for scalable pagination.
Home-page: https://github.com/nitely/django-infinite-scroll-pagination
Author: Esteban Castro Borsani
Author-email: ecastroborsani@gmail.com
License: MIT License
Platform: UNKNOWN
Classifier: Development Status :: 5 - Production/Stable
Classifier: Environment :: Web Environment
Classifier: Framework :: Django
Classifier: Intended Audience :: Developers
Classifier: License :: OSI Approved :: MIT License
Classifier: Operating System :: OS Independent
Classifier: Programming Language :: Python
Classifier: Programming Language :: Python :: 3
Classifier: Topic :: Internet :: WWW/HTTP
Classifier: Topic :: Internet :: WWW/HTTP :: Dynamic Content
